linea_tiempo/__init__.py
linea_tiempo/generador.py
linea_tiempo_pptx-0.3.3.dist-info/licenses/LICENSE.TXT
linea_tiempo_pptx-0.3.3.dist-info/METADATA
linea_tiempo_pptx-0.3.3.dist-info/WHEEL
linea_tiempo_pptx-0.3.3.dist-info/entry_points.txt
linea_tiempo_pptx-0.3.3.dist-info/top_level.txt
linea_tiempo_pptx-0.3.3.dist-info/RECORD
