Metadata-Version: 2.4
Name: linea_tiempo_pptx
Version: 0.3.3
Summary: Generador de líneas de tiempo en PowerPoint desde Excel
Home-page: https://github.com/jhonyzavala/linea_tiempo
Author: Jhony Zavala
Classifier: Programming Language :: Python :: 3
Classifier: License :: OSI Approved :: MIT License
Requires-Python: >=3.7
License-File: LICENSE.TXT
Requires-Dist: pandas
Requires-Dist: python-pptx
Requires-Dist: openpyxl
Dynamic: author
Dynamic: classifier
Dynamic: description
Dynamic: description-content-type
Dynamic: home-page
Dynamic: license-file
Dynamic: requires-dist
Dynamic: requires-python
Dynamic: summary
